MANIFEST.in
README.md
setup.py
app_init_auth.egg-info/PKG-INFO
app_init_auth.egg-info/SOURCES.txt
app_init_auth.egg-info/dependency_links.txt
app_init_auth.egg-info/entry_points.txt
app_init_auth.egg-info/not-zip-safe
app_init_auth.egg-info/requires.txt
app_init_auth.egg-info/top_level.txt
webplatform_auth/__init__.py
webplatform_auth/cli.py
webplatform_auth/app/__init__.py
webplatform_auth/app/app.py
webplatform_auth/app/api/__init__.py
webplatform_auth/app/api/users/__init__.py
webplatform_auth/app/api/users/change_user.py
webplatform_auth/app/api/users/get.py
webplatform_auth/app/api/users/list.py
webplatform_auth/app/api/users/picture.py
webplatform_auth/app/api/users/search.py
webplatform_auth/app/api/users/timezone.py
webplatform_auth/app/api/users/permissions/__init__.py
webplatform_auth/app/api/users/permissions/add.py
webplatform_auth/app/api/users/permissions/get.py
webplatform_auth/app/api/users/permissions/list.py
webplatform_auth/app/api/users/permissions/remove.py
webplatform_auth/app/api/users/token/__init__.py
webplatform_auth/app/api/users/token/renew.py
webplatform_auth/app/views/__init__.py
webplatform_auth/app/views/saml.py
webplatform_auth/container/data/README.md
webplatform_auth/container/docker/actions/auth/build.sh
webplatform_auth/container/docker/actions/auth/entry.sh
webplatform_auth/container/docker/actions/auth/restart.sh
webplatform_auth/container/docker/actions/auth/start.sh
webplatform_auth/container/docker/actions/auth/stop.sh
webplatform_auth/container/docker/actions/auth/update.sh
webplatform_auth/container/docker/auth/gunicorn.py
webplatform_auth/container/docker/auth/saml/settings.json
webplatform_auth/container/docker/auth/saml/sp.crt
webplatform_auth/container/docker/auth/saml/sp.key
webplatform_auth/container/settings/auth.json
webplatform_auth/container/settings/cli.json
webplatform_auth/container/settings/variables.json
webplatform_auth/lib/__init__.py
webplatform_auth/lib/base_user.py
webplatform_auth/lib/permissions.py
webplatform_auth/lib/session.py
webplatform_auth/lib/user.py
webplatform_auth/lib/permissions_apis/__init__.py
webplatform_auth/lib/permissions_apis/setup.py
webplatform_auth/lib/permissions_apis/apis/__init__.py
